[[{"link_1":"973","poblacion":"2227","hombres":"1104","mujeres":"1123","0_4":"161","5_9":"164","10_14":"193","15_19":"163","20_24":"166","25_29":"188","30_34":"136","35_39":"143","40_44":"141","45_49":"118","50_54":"107","55_59":"106","60_64":"123","65_69":"96","70_74":"81","75_79":"68","80_84":"46","85_89":"22","90_94":"4","95_mas":"1","id":"213","tabla":"set_1","autor_id":"2","referente_id":"1","titulo":"Censo 2008 C\u00f3rdoba","descripcion":"Datos extraidos del censo 2008 realizado en C\u00f3rdoba por el gobierno provincial","url":"http:\/\/web2.cba.gov.ar\/actual_web\/estadisticas\/censo2008\/index.html"}],[{"link_1":"973","Total Viviendas":"707","Casa":"699","Rancho":"1","Casilla":"0","Departamento":"3","Inquilinato":"3","Pension":"0","Local no construido para habitacion":"1","Vivienda movil":"0","En la calle":"0","id":"213","tabla":"set_2","autor_id":"2","referente_id":"1","titulo":"Censo 2008 C\u00f3rdoba Viviendas","descripcion":"Datos extraidos del censo 2008 realizado en C\u00f3rdoba por el gobierno provincial. \r\nDetalle de la cantidad total y los tipos de viviendas por ciudad","url":"http:\/\/web2.cba.gov.ar\/actual_web\/estadisticas\/censo2008\/index.html"}],[],[],[{"link_1":"973","Nunca Asistio":"135","Inicial":"51","Primario incompleto":"476","Primario completo":"525","Secundario incompleto":"398","Secundario completo":"249","Terciario incompleto":"52","Terciario completo":"126","Universitario incompleto":"61","Universitario completo":"46","Postgrado universitario incompleto":"3","Postgrado universitario completo":"4","Educacion especial incompleto":"4","Educaci\u00f3n especial completo":"1","Ignorado":"12","id":"213","tabla":"set_3","autor_id":"2","referente_id":"1","titulo":"Censo 2008 C\u00f3rdoba Estudios","descripcion":"Datos extra\u00eddos del censo 2008 realizado en C\u00f3rdoba por el gobierno provincial.\r\nSolo poblaci\u00f3n de tres o m\u00e1s a\u00f1os. \r\nInformaci\u00f3n a cerca del m\u00e1ximo nivel de estudios alcanzados por las poblaciones de cada ciudad","url":"http:\/\/web2.cba.gov.ar\/actual_web\/estadisticas\/censo2008\/index.html"}],[]]