[[{"link_1":"490","poblacion":"5179","hombres":"2554","mujeres":"2625","0_4":"315","5_9":"346","10_14":"346","15_19":"406","20_24":"355","25_29":"364","30_34":"346","35_39":"298","40_44":"289","45_49":"326","50_54":"312","55_59":"304","60_64":"270","65_69":"255","70_74":"227","75_79":"178","80_84":"138","85_89":"72","90_94":"23","95_mas":"9","id":"216","tabla":"set_1","autor_id":"2","referente_id":"1","titulo":"Censo 2008 C\u00f3rdoba","descripcion":"Datos extraidos del censo 2008 realizado en C\u00f3rdoba por el gobierno provincial","url":"http:\/\/web2.cba.gov.ar\/actual_web\/estadisticas\/censo2008\/index.html"}],[{"link_1":"490","Total Viviendas":"1986","Casa":"1966","Rancho":"3","Casilla":"0","Departamento":"0","Inquilinato":"2","Pension":"0","Local no construido para habitacion":"15","Vivienda movil":"0","En la calle":"0","id":"216","tabla":"set_2","autor_id":"2","referente_id":"1","titulo":"Censo 2008 C\u00f3rdoba Viviendas","descripcion":"Datos extraidos del censo 2008 realizado en C\u00f3rdoba por el gobierno provincial. \r\nDetalle de la cantidad total y los tipos de viviendas por ciudad","url":"http:\/\/web2.cba.gov.ar\/actual_web\/estadisticas\/censo2008\/index.html"}],[],[],[{"link_1":"490","Nunca Asistio":"295","Inicial":"116","Primario incompleto":"1088","Primario completo":"1109","Secundario incompleto":"817","Secundario completo":"790","Terciario incompleto":"85","Terciario completo":"297","Universitario incompleto":"177","Universitario completo":"164","Postgrado universitario incompleto":"5","Postgrado universitario completo":"11","Educacion especial incompleto":"11","Educaci\u00f3n especial completo":"4","Ignorado":"28","id":"216","tabla":"set_3","autor_id":"2","referente_id":"1","titulo":"Censo 2008 C\u00f3rdoba Estudios","descripcion":"Datos extra\u00eddos del censo 2008 realizado en C\u00f3rdoba por el gobierno provincial.\r\nSolo poblaci\u00f3n de tres o m\u00e1s a\u00f1os. \r\nInformaci\u00f3n a cerca del m\u00e1ximo nivel de estudios alcanzados por las poblaciones de cada ciudad","url":"http:\/\/web2.cba.gov.ar\/actual_web\/estadisticas\/censo2008\/index.html"}],[]]