[[{"link_1":"833","poblacion":"2234","hombres":"1099","mujeres":"1135","0_4":"152","5_9":"152","10_14":"205","15_19":"187","20_24":"161","25_29":"165","30_34":"132","35_39":"123","40_44":"155","45_49":"143","50_54":"135","55_59":"100","60_64":"133","65_69":"85","70_74":"80","75_79":"60","80_84":"38","85_89":"20","90_94":"5","95_mas":"3","id":"366","tabla":"set_1","autor_id":"2","referente_id":"1","titulo":"Censo 2008 C\u00f3rdoba","descripcion":"Datos extraidos del censo 2008 realizado en C\u00f3rdoba por el gobierno provincial","url":"http:\/\/web2.cba.gov.ar\/actual_web\/estadisticas\/censo2008\/index.html"}],[{"link_1":"833","Total Viviendas":"719","Casa":"718","Rancho":"0","Casilla":"1","Departamento":"0","Inquilinato":"0","Pension":"0","Local no construido para habitacion":"0","Vivienda movil":"0","En la calle":"0","id":"366","tabla":"set_2","autor_id":"2","referente_id":"1","titulo":"Censo 2008 C\u00f3rdoba Viviendas","descripcion":"Datos extraidos del censo 2008 realizado en C\u00f3rdoba por el gobierno provincial. \r\nDetalle de la cantidad total y los tipos de viviendas por ciudad","url":"http:\/\/web2.cba.gov.ar\/actual_web\/estadisticas\/censo2008\/index.html"}],[],[],[{"link_1":"833","Nunca Asistio":"133","Inicial":"49","Primario incompleto":"527","Primario completo":"523","Secundario incompleto":"442","Secundario completo":"172","Terciario incompleto":"37","Terciario completo":"50","Universitario incompleto":"106","Universitario completo":"62","Postgrado universitario incompleto":"0","Postgrado universitario completo":"3","Educacion especial incompleto":"2","Educaci\u00f3n especial completo":"0","Ignorado":"37","id":"366","tabla":"set_3","autor_id":"2","referente_id":"1","titulo":"Censo 2008 C\u00f3rdoba Estudios","descripcion":"Datos extra\u00eddos del censo 2008 realizado en C\u00f3rdoba por el gobierno provincial.\r\nSolo poblaci\u00f3n de tres o m\u00e1s a\u00f1os. \r\nInformaci\u00f3n a cerca del m\u00e1ximo nivel de estudios alcanzados por las poblaciones de cada ciudad","url":"http:\/\/web2.cba.gov.ar\/actual_web\/estadisticas\/censo2008\/index.html"}],[]]