[[{"link_1":"1344","poblacion":"2413","hombres":"1153","mujeres":"1260","0_4":"182","5_9":"214","10_14":"203","15_19":"168","20_24":"140","25_29":"167","30_34":"157","35_39":"131","40_44":"131","45_49":"136","50_54":"113","55_59":"130","60_64":"122","65_69":"128","70_74":"109","75_79":"86","80_84":"60","85_89":"26","90_94":"8","95_mas":"2","id":"521","tabla":"set_1","autor_id":"2","referente_id":"1","titulo":"Censo 2008 C\u00f3rdoba","descripcion":"Datos extraidos del censo 2008 realizado en C\u00f3rdoba por el gobierno provincial","url":"http:\/\/web2.cba.gov.ar\/actual_web\/estadisticas\/censo2008\/index.html"}],[{"link_1":"1344","Total Viviendas":"834","Casa":"813","Rancho":"15","Casilla":"0","Departamento":"2","Inquilinato":"3","Pension":"0","Local no construido para habitacion":"1","Vivienda movil":"0","En la calle":"0","id":"521","tabla":"set_2","autor_id":"2","referente_id":"1","titulo":"Censo 2008 C\u00f3rdoba Viviendas","descripcion":"Datos extraidos del censo 2008 realizado en C\u00f3rdoba por el gobierno provincial. \r\nDetalle de la cantidad total y los tipos de viviendas por ciudad","url":"http:\/\/web2.cba.gov.ar\/actual_web\/estadisticas\/censo2008\/index.html"}],[],[],[{"link_1":"1344","Nunca Asistio":"150","Inicial":"79","Primario incompleto":"560","Primario completo":"651","Secundario incompleto":"354","Secundario completo":"248","Terciario incompleto":"49","Terciario completo":"107","Universitario incompleto":"29","Universitario completo":"34","Postgrado universitario incompleto":"1","Postgrado universitario completo":"5","Educacion especial incompleto":"1","Educaci\u00f3n especial completo":"1","Ignorado":"32","id":"521","tabla":"set_3","autor_id":"2","referente_id":"1","titulo":"Censo 2008 C\u00f3rdoba Estudios","descripcion":"Datos extra\u00eddos del censo 2008 realizado en C\u00f3rdoba por el gobierno provincial.\r\nSolo poblaci\u00f3n de tres o m\u00e1s a\u00f1os. \r\nInformaci\u00f3n a cerca del m\u00e1ximo nivel de estudios alcanzados por las poblaciones de cada ciudad","url":"http:\/\/web2.cba.gov.ar\/actual_web\/estadisticas\/censo2008\/index.html"}],[]]