[[{"link_1":"1533","poblacion":"1342","hombres":"671","mujeres":"671","0_4":"116","5_9":"138","10_14":"133","15_19":"119","20_24":"106","25_29":"105","30_34":"109","35_39":"109","40_44":"80","45_49":"60","50_54":"48","55_59":"49","60_64":"62","65_69":"35","70_74":"33","75_79":"14","80_84":"13","85_89":"9","90_94":"4","95_mas":"0","id":"530","tabla":"set_1","autor_id":"2","referente_id":"1","titulo":"Censo 2008 C\u00f3rdoba","descripcion":"Datos extraidos del censo 2008 realizado en C\u00f3rdoba por el gobierno provincial","url":"http:\/\/web2.cba.gov.ar\/actual_web\/estadisticas\/censo2008\/index.html"}],[{"link_1":"1533","Total Viviendas":"354","Casa":"343","Rancho":"4","Casilla":"0","Departamento":"3","Inquilinato":"4","Pension":"0","Local no construido para habitacion":"0","Vivienda movil":"0","En la calle":"0","id":"530","tabla":"set_2","autor_id":"2","referente_id":"1","titulo":"Censo 2008 C\u00f3rdoba Viviendas","descripcion":"Datos extraidos del censo 2008 realizado en C\u00f3rdoba por el gobierno provincial. \r\nDetalle de la cantidad total y los tipos de viviendas por ciudad","url":"http:\/\/web2.cba.gov.ar\/actual_web\/estadisticas\/censo2008\/index.html"}],[],[],[{"link_1":"1533","Nunca Asistio":"87","Inicial":"47","Primario incompleto":"272","Primario completo":"314","Secundario incompleto":"263","Secundario completo":"113","Terciario incompleto":"30","Terciario completo":"33","Universitario incompleto":"37","Universitario completo":"51","Postgrado universitario incompleto":"4","Postgrado universitario completo":"3","Educacion especial incompleto":"1","Educaci\u00f3n especial completo":"0","Ignorado":"12","id":"530","tabla":"set_3","autor_id":"2","referente_id":"1","titulo":"Censo 2008 C\u00f3rdoba Estudios","descripcion":"Datos extra\u00eddos del censo 2008 realizado en C\u00f3rdoba por el gobierno provincial.\r\nSolo poblaci\u00f3n de tres o m\u00e1s a\u00f1os. \r\nInformaci\u00f3n a cerca del m\u00e1ximo nivel de estudios alcanzados por las poblaciones de cada ciudad","url":"http:\/\/web2.cba.gov.ar\/actual_web\/estadisticas\/censo2008\/index.html"}],[]]