[[{"link_1":"1358","poblacion":"3031","hombres":"1494","mujeres":"1537","0_4":"306","5_9":"292","10_14":"258","15_19":"234","20_24":"231","25_29":"276","30_34":"189","35_39":"150","40_44":"192","45_49":"154","50_54":"155","55_59":"165","60_64":"126","65_69":"94","70_74":"77","75_79":"74","80_84":"29","85_89":"22","90_94":"5","95_mas":"2","id":"544","tabla":"set_1","autor_id":"2","referente_id":"1","titulo":"Censo 2008 C\u00f3rdoba","descripcion":"Datos extraidos del censo 2008 realizado en C\u00f3rdoba por el gobierno provincial","url":"http:\/\/web2.cba.gov.ar\/actual_web\/estadisticas\/censo2008\/index.html"}],[{"link_1":"1358","Total Viviendas":"951","Casa":"917","Rancho":"13","Casilla":"0","Departamento":"13","Inquilinato":"1","Pension":"1","Local no construido para habitacion":"6","Vivienda movil":"0","En la calle":"0","id":"544","tabla":"set_2","autor_id":"2","referente_id":"1","titulo":"Censo 2008 C\u00f3rdoba Viviendas","descripcion":"Datos extraidos del censo 2008 realizado en C\u00f3rdoba por el gobierno provincial. \r\nDetalle de la cantidad total y los tipos de viviendas por ciudad","url":"http:\/\/web2.cba.gov.ar\/actual_web\/estadisticas\/censo2008\/index.html"}],[],[],[{"link_1":"1358","Nunca Asistio":"217","Inicial":"100","Primario incompleto":"628","Primario completo":"778","Secundario incompleto":"530","Secundario completo":"327","Terciario incompleto":"49","Terciario completo":"72","Universitario incompleto":"65","Universitario completo":"46","Postgrado universitario incompleto":"1","Postgrado universitario completo":"4","Educacion especial incompleto":"6","Educaci\u00f3n especial completo":"2","Ignorado":"19","id":"544","tabla":"set_3","autor_id":"2","referente_id":"1","titulo":"Censo 2008 C\u00f3rdoba Estudios","descripcion":"Datos extra\u00eddos del censo 2008 realizado en C\u00f3rdoba por el gobierno provincial.\r\nSolo poblaci\u00f3n de tres o m\u00e1s a\u00f1os. \r\nInformaci\u00f3n a cerca del m\u00e1ximo nivel de estudios alcanzados por las poblaciones de cada ciudad","url":"http:\/\/web2.cba.gov.ar\/actual_web\/estadisticas\/censo2008\/index.html"}],[]]