[[{"link_1":"749","poblacion":"4895","hombres":"2414","mujeres":"2481","0_4":"412","5_9":"414","10_14":"432","15_19":"459","20_24":"287","25_29":"292","30_34":"323","35_39":"333","40_44":"298","45_49":"303","50_54":"273","55_59":"250","60_64":"221","65_69":"193","70_74":"149","75_79":"120","80_84":"75","85_89":"37","90_94":"12","95_mas":"12","id":"576","tabla":"set_1","autor_id":"2","referente_id":"1","titulo":"Censo 2008 C\u00f3rdoba","descripcion":"Datos extraidos del censo 2008 realizado en C\u00f3rdoba por el gobierno provincial","url":"http:\/\/web2.cba.gov.ar\/actual_web\/estadisticas\/censo2008\/index.html"}],[{"link_1":"749","Total Viviendas":"1662","Casa":"1576","Rancho":"15","Casilla":"9","Departamento":"60","Inquilinato":"0","Pension":"0","Local no construido para habitacion":"2","Vivienda movil":"0","En la calle":"0","id":"576","tabla":"set_2","autor_id":"2","referente_id":"1","titulo":"Censo 2008 C\u00f3rdoba Viviendas","descripcion":"Datos extraidos del censo 2008 realizado en C\u00f3rdoba por el gobierno provincial. \r\nDetalle de la cantidad total y los tipos de viviendas por ciudad","url":"http:\/\/web2.cba.gov.ar\/actual_web\/estadisticas\/censo2008\/index.html"}],[],[],[{"link_1":"749","Nunca Asistio":"289","Inicial":"213","Primario incompleto":"744","Primario completo":"917","Secundario incompleto":"994","Secundario completo":"658","Terciario incompleto":"116","Terciario completo":"278","Universitario incompleto":"174","Universitario completo":"194","Postgrado universitario incompleto":"11","Postgrado universitario completo":"24","Educacion especial incompleto":"3","Educaci\u00f3n especial completo":"0","Ignorado":"48","id":"576","tabla":"set_3","autor_id":"2","referente_id":"1","titulo":"Censo 2008 C\u00f3rdoba Estudios","descripcion":"Datos extra\u00eddos del censo 2008 realizado en C\u00f3rdoba por el gobierno provincial.\r\nSolo poblaci\u00f3n de tres o m\u00e1s a\u00f1os. \r\nInformaci\u00f3n a cerca del m\u00e1ximo nivel de estudios alcanzados por las poblaciones de cada ciudad","url":"http:\/\/web2.cba.gov.ar\/actual_web\/estadisticas\/censo2008\/index.html"}],[]]