[{"provincia":"C\u00f3rdoba","municipio":"Piquill\u00edn","id":"456","link_1":"931","Nunca Asistio":"84","Inicial":"30","Primario incompleto":"251","Primario completo":"315","Secundario incompleto":"302","Secundario completo":"136","Terciario incompleto":"32","Terciario completo":"53","Universitario incompleto":"41","Universitario completo":"15","Postgrado universitario incompleto":"0","Postgrado universitario completo":"0","Educacion especial incompleto":"1","Educaci\u00f3n especial completo":"1","Ignorado":"17"}]